antibodyomics/__init__.py
antibodyomics/example.py
antibodyomics_test/__init__.py
antibodyomics_test/example.py
antibodyomics-0.0.1.1.dist-info/LICENSE
antibodyomics-0.0.1.1.dist-info/METADATA
antibodyomics-0.0.1.1.dist-info/WHEEL
antibodyomics-0.0.1.1.dist-info/top_level.txt
antibodyomics-0.0.1.1.dist-info/RECORD
